[{"dir": "./data/expand_data/test_set\\00000.jpg", "label": "-1"}, {"dir": "./data/expand_data/test_set\\00001.jpg", "label": "-1"}, {"dir": "./data/expand_data/test_set\\00002.jpg", "label": "-1"}, {"dir": "./data/expand_data/test_set\\00003.jpg", "label": "-1"}, {"dir": "./data/expand_data/test_set\\00004.jpg", "label": "-1"}, {"dir": "./data/expand_data/test_set\\00005.jpg", "label": "-1"}, {"dir": "./data/expand_data/test_set\\00006.jpg", "label": "-1"}, {"dir": "./data/expand_data/test_set\\00007.jpg", "label": "-1"}, {"dir": "./data/expand_data/test_set\\00008.jpg", "label": "-1"}, {"dir": "./data/expand_data/test_set\\00009.jpg", "label": "-1"}, {"dir": "./data/expand_data/test_set\\00010.jpg", "label": "-1"}, {"dir": "./data/expand_data/test_set\\00011.jpg", "label": "-1"}, {"dir": "./data/expand_data/test_set\\00012.jpg", "label": "-1"}, {"dir": "./data/expand_data/test_set\\00013.jpg", "label": "-1"}, {"dir": "./data/expand_data/test_set\\00014.jpg", "label": "-1"}, {"dir": "./data/expand_data/test_set\\00015.jpg", "label": "-1"}, {"dir": "./data/expand_data/test_set\\00016.jpg", "label": "-1"}, {"dir": "./data/expand_data/test_set\\00017.jpg", "label": "-1"}, {"dir": "./data/expand_data/test_set\\00018.jpg", "label": "-1"}, {"dir": "./data/expand_data/test_set\\00019.jpg", "label": "-1"}, {"dir": "./data/expand_data/test_set\\00020.jpg", "label": "-1"}, {"dir": "./data/expand_data/test_set\\00021.jpg", "label": "-1"}, {"dir": "./data/expand_data/test_set\\00022.jpg", "label": "-1"}, {"dir": "./data/expand_data/test_set\\00023.jpg", "label": "-1"}, {"dir": "./data/expand_data/test_set\\00024.jpg", "label": "-1"}, {"dir": "./data/expand_data/test_set\\00025.jpg", "label": "-1"}, {"dir": "./data/expand_data/test_set\\00026.jpg", "label": "-1"}, {"dir": "./data/expand_data/test_set\\00027.jpg", "label": "-1"}, {"dir": "./data/expand_data/test_set\\00028.jpg", "label": "-1"}, {"dir": "./data/expand_data/test_set\\00029.jpg", "label": "-1"}, {"dir": "./data/expand_data/test_set\\00030.jpg", "label": "-1"}, {"dir": "./data/expand_data/test_set\\00031.jpg", "label": "-1"}, {"dir": "./data/expand_data/test_set\\00032.jpg", "label": "-1"}, {"dir": "./data/expand_data/test_set\\00033.jpg", "label": "-1"}, {"dir": "./data/expand_data/test_set\\00034.jpg", "label": "-1"}, {"dir": "./data/expand_data/test_set\\00035.jpg", "label": "-1"}, {"dir": "./data/expand_data/test_set\\00036.jpg", "label": "-1"}, {"dir": "./data/expand_data/test_set\\00037.jpg", "label": "-1"}, {"dir": "./data/expand_data/test_set\\00038.jpg", "label": "-1"}, {"dir": "./data/expand_data/test_set\\00039.jpg", "label": "-1"}, {"dir": "./data/expand_data/test_set\\00040.jpg", "label": "-1"}, {"dir": "./data/expand_data/test_set\\00041.jpg", "label": "-1"}, {"dir": "./data/expand_data/test_set\\00042.jpg", "label": "-1"}, {"dir": "./data/expand_data/test_set\\00043.jpg", "label": "-1"}, {"dir": "./data/expand_data/test_set\\00044.jpg", "label": "-1"}, {"dir": "./data/expand_data/test_set\\00045.jpg", "label": "-1"}, {"dir": "./data/expand_data/test_set\\00046.jpg", "label": "-1"}, {"dir": "./data/expand_data/test_set\\00047.jpg", "label": "-1"}, {"dir": "./data/expand_data/test_set\\00048.jpg", "label": "-1"}, {"dir": "./data/expand_data/test_set\\00049.jpg", "label": "-1"}, {"dir": "./data/expand_data/test_set\\00050.jpg", "label": "-1"}, {"dir": "./data/expand_data/test_set\\00051.jpg", "label": "-1"}, {"dir": "./data/expand_data/test_set\\00052.jpg", "label": "-1"}, {"dir": "./data/expand_data/test_set\\00053.jpg", "label": "-1"}, {"dir": "./data/expand_data/test_set\\00054.jpg", "label": "-1"}, {"dir": "./data/expand_data/test_set\\00055.jpg", "label": "-1"}, {"dir": "./data/expand_data/test_set\\00056.jpg", "label": "-1"}, {"dir": "./data/expand_data/test_set\\00057.jpg", "label": "-1"}, {"dir": "./data/expand_data/test_set\\00058.jpg", "label": "-1"}, {"dir": "./data/expand_data/test_set\\00059.jpg", "label": "-1"}, {"dir": "./data/expand_data/test_set\\00060.jpg", "label": "-1"}, {"dir": "./data/expand_data/test_set\\00061.jpg", "label": "-1"}, {"dir": "./data/expand_data/test_set\\00062.jpg", "label": "-1"}, {"dir": "./data/expand_data/test_set\\00063.jpg", "label": "-1"}, {"dir": "./data/expand_data/test_set\\00064.jpg", "label": "-1"}, {"dir": "./data/expand_data/test_set\\00065.jpg", "label": "-1"}, {"dir": "./data/expand_data/test_set\\00066.jpg", "label": "-1"}, {"dir": "./data/expand_data/test_set\\00067.jpg", "label": "-1"}, {"dir": "./data/expand_data/test_set\\00068.jpg", "label": "-1"}, {"dir": "./data/expand_data/test_set\\00069.jpg", "label": "-1"}, {"dir": "./data/expand_data/test_set\\00070.jpg", "label": "-1"}, {"dir": "./data/expand_data/test_set\\00071.jpg", "label": "-1"}, {"dir": "./data/expand_data/test_set\\00072.jpg", "label": "-1"}, {"dir": "./data/expand_data/test_set\\00073.jpg", "label": "-1"}, {"dir": "./data/expand_data/test_set\\00074.jpg", "label": "-1"}, {"dir": "./data/expand_data/test_set\\00075.jpg", "label": "-1"}, {"dir": "./data/expand_data/test_set\\00076.jpg", "label": "-1"}, {"dir": "./data/expand_data/test_set\\00077.jpg", "label": "-1"}, {"dir": "./data/expand_data/test_set\\00078.jpg", "label": "-1"}, {"dir": "./data/expand_data/test_set\\00079.jpg", "label": "-1"}, {"dir": "./data/expand_data/test_set\\00080.jpg", "label": "-1"}, {"dir": "./data/expand_data/test_set\\00081.jpg", "label": "-1"}, {"dir": "./data/expand_data/test_set\\00082.jpg", "label": "-1"}, {"dir": "./data/expand_data/test_set\\00083.jpg", "label": "-1"}, {"dir": "./data/expand_data/test_set\\00084.jpg", "label": "-1"}, {"dir": "./data/expand_data/test_set\\00085.jpg", "label": "-1"}, {"dir": "./data/expand_data/test_set\\00086.jpg", "label": "-1"}, {"dir": "./data/expand_data/test_set\\00087.jpg", "label": "-1"}, {"dir": "./data/expand_data/test_set\\00088.jpg", "label": "-1"}, {"dir": "./data/expand_data/test_set\\00089.jpg", "label": "-1"}, {"dir": "./data/expand_data/test_set\\00090.jpg", "label": "-1"}, {"dir": "./data/expand_data/test_set\\00091.jpg", "label": "-1"}, {"dir": "./data/expand_data/test_set\\00092.jpg", "label": "-1"}, {"dir": "./data/expand_data/test_set\\00093.jpg", "label": "-1"}, {"dir": "./data/expand_data/test_set\\00094.jpg", "label": "-1"}, {"dir": "./data/expand_data/test_set\\00095.jpg", "label": "-1"}, {"dir": "./data/expand_data/test_set\\00096.jpg", "label": "-1"}, {"dir": "./data/expand_data/test_set\\00097.jpg", "label": "-1"}, {"dir": "./data/expand_data/test_set\\00098.jpg", "label": "-1"}, {"dir": "./data/expand_data/test_set\\00099.jpg", "label": "-1"}, {"dir": "./data/expand_data/test_set\\00100.jpg", "label": "-1"}, {"dir": "./data/expand_data/test_set\\00101.jpg", "label": "-1"}, {"dir": "./data/expand_data/test_set\\00102.jpg", "label": "-1"}, {"dir": "./data/expand_data/test_set\\00103.jpg", "label": "-1"}, {"dir": "./data/expand_data/test_set\\00104.jpg", "label": "-1"}, {"dir": "./data/expand_data/test_set\\00105.jpg", "label": "-1"}, {"dir": "./data/expand_data/test_set\\00106.jpg", "label": "-1"}, {"dir": "./data/expand_data/test_set\\00107.jpg", "label": "-1"}, {"dir": "./data/expand_data/test_set\\00108.jpg", "label": "-1"}, {"dir": "./data/expand_data/test_set\\00109.jpg", "label": "-1"}, {"dir": "./data/expand_data/test_set\\00110.jpg", "label": "-1"}, {"dir": "./data/expand_data/test_set\\00111.jpg", "label": "-1"}, {"dir": "./data/expand_data/test_set\\00112.jpg", "label": "-1"}, {"dir": "./data/expand_data/test_set\\00113.jpg", "label": "-1"}, {"dir": "./data/expand_data/test_set\\00114.jpg", "label": "-1"}, {"dir": "./data/expand_data/test_set\\00115.jpg", "label": "-1"}, {"dir": "./data/expand_data/test_set\\00116.jpg", "label": "-1"}, {"dir": "./data/expand_data/test_set\\00117.jpg", "label": "-1"}, {"dir": "./data/expand_data/test_set\\00118.jpg", "label": "-1"}, {"dir": "./data/expand_data/test_set\\00119.jpg", "label": "-1"}, {"dir": "./data/expand_data/test_set\\00120.jpg", "label": "-1"}, {"dir": "./data/expand_data/test_set\\00121.jpg", "label": "-1"}, {"dir": "./data/expand_data/test_set\\00122.jpg", "label": "-1"}, {"dir": "./data/expand_data/test_set\\00123.jpg", "label": "-1"}, {"dir": "./data/expand_data/test_set\\00124.jpg", "label": "-1"}, {"dir": "./data/expand_data/test_set\\00125.jpg", "label": "-1"}, {"dir": "./data/expand_data/test_set\\00126.jpg", "label": "-1"}, {"dir": "./data/expand_data/test_set\\00127.jpg", "label": "-1"}, {"dir": "./data/expand_data/test_set\\00128.jpg", "label": "-1"}, {"dir": "./data/expand_data/test_set\\00129.jpg", "label": "-1"}, {"dir": "./data/expand_data/test_set\\00130.jpg", "label": "-1"}, {"dir": "./data/expand_data/test_set\\00131.jpg", "label": "-1"}, {"dir": "./data/expand_data/test_set\\00132.jpg", "label": "-1"}, {"dir": "./data/expand_data/test_set\\00133.jpg", "label": "-1"}, {"dir": "./data/expand_data/test_set\\00134.jpg", "label": "-1"}, {"dir": "./data/expand_data/test_set\\00135.jpg", "label": "-1"}, {"dir": "./data/expand_data/test_set\\00136.jpg", "label": "-1"}, {"dir": "./data/expand_data/test_set\\00137.jpg", "label": "-1"}, {"dir": "./data/expand_data/test_set\\00138.jpg", "label": "-1"}, {"dir": "./data/expand_data/test_set\\00139.jpg", "label": "-1"}, {"dir": "./data/expand_data/test_set\\00140.jpg", "label": "-1"}, {"dir": "./data/expand_data/test_set\\00141.jpg", "label": "-1"}, {"dir": "./data/expand_data/test_set\\00142.jpg", "label": "-1"}, {"dir": "./data/expand_data/test_set\\00143.jpg", "label": "-1"}, {"dir": "./data/expand_data/test_set\\00144.jpg", "label": "-1"}, {"dir": "./data/expand_data/test_set\\00145.jpg", "label": "-1"}, {"dir": "./data/expand_data/test_set\\00146.jpg", "label": "-1"}, {"dir": "./data/expand_data/test_set\\00147.jpg", "label": "-1"}, {"dir": "./data/expand_data/test_set\\00148.jpg", "label": "-1"}, {"dir": "./data/expand_data/test_set\\00149.jpg", "label": "-1"}, {"dir": "./data/expand_data/test_set\\00150.jpg", "label": "-1"}, {"dir": "./data/expand_data/test_set\\00151.jpg", "label": "-1"}, {"dir": "./data/expand_data/test_set\\00152.jpg", "label": "-1"}, {"dir": "./data/expand_data/test_set\\00153.jpg", "label": "-1"}, {"dir": "./data/expand_data/test_set\\00154.jpg", "label": "-1"}, {"dir": "./data/expand_data/test_set\\00155.jpg", "label": "-1"}, {"dir": "./data/expand_data/test_set\\00156.jpg", "label": "-1"}, {"dir": "./data/expand_data/test_set\\00157.jpg", "label": "-1"}, {"dir": "./data/expand_data/test_set\\00158.jpg", "label": "-1"}, {"dir": "./data/expand_data/test_set\\00159.jpg", "label": "-1"}, {"dir": "./data/expand_data/test_set\\00160.jpg", "label": "-1"}, {"dir": "./data/expand_data/test_set\\00161.jpg", "label": "-1"}, {"dir": "./data/expand_data/test_set\\00162.jpg", "label": "-1"}, {"dir": "./data/expand_data/test_set\\00163.jpg", "label": "-1"}, {"dir": "./data/expand_data/test_set\\00164.jpg", "label": "-1"}, {"dir": "./data/expand_data/test_set\\00165.jpg", "label": "-1"}, {"dir": "./data/expand_data/test_set\\00166.jpg", "label": "-1"}, {"dir": "./data/expand_data/test_set\\00167.jpg", "label": "-1"}, {"dir": "./data/expand_data/test_set\\00168.jpg", "label": "-1"}, {"dir": "./data/expand_data/test_set\\00169.jpg", "label": "-1"}, {"dir": "./data/expand_data/test_set\\00170.jpg", "label": "-1"}, {"dir": "./data/expand_data/test_set\\00171.jpg", "label": "-1"}, {"dir": "./data/expand_data/test_set\\00172.jpg", "label": "-1"}, {"dir": "./data/expand_data/test_set\\00173.jpg", "label": "-1"}, {"dir": "./data/expand_data/test_set\\00174.jpg", "label": "-1"}, {"dir": "./data/expand_data/test_set\\00175.jpg", "label": "-1"}, {"dir": "./data/expand_data/test_set\\00176.jpg", "label": "-1"}, {"dir": "./data/expand_data/test_set\\00177.jpg", "label": "-1"}, {"dir": "./data/expand_data/test_set\\00178.jpg", "label": "-1"}, {"dir": "./data/expand_data/test_set\\00179.jpg", "label": "-1"}, {"dir": "./data/expand_data/test_set\\00180.jpg", "label": "-1"}, {"dir": "./data/expand_data/test_set\\00181.jpg", "label": "-1"}, {"dir": "./data/expand_data/test_set\\00182.jpg", "label": "-1"}, {"dir": "./data/expand_data/test_set\\00183.jpg", "label": "-1"}, {"dir": "./data/expand_data/test_set\\00184.jpg", "label": "-1"}, {"dir": "./data/expand_data/test_set\\00185.jpg", "label": "-1"}, {"dir": "./data/expand_data/test_set\\00186.jpg", "label": "-1"}, {"dir": "./data/expand_data/test_set\\00187.jpg", "label": "-1"}, {"dir": "./data/expand_data/test_set\\00188.jpg", "label": "-1"}, {"dir": "./data/expand_data/test_set\\00189.jpg", "label": "-1"}, {"dir": "./data/expand_data/test_set\\00190.jpg", "label": "-1"}, {"dir": "./data/expand_data/test_set\\00191.jpg", "label": "-1"}, {"dir": "./data/expand_data/test_set\\00192.jpg", "label": "-1"}, {"dir": "./data/expand_data/test_set\\00193.jpg", "label": "-1"}, {"dir": "./data/expand_data/test_set\\00194.jpg", "label": "-1"}, {"dir": "./data/expand_data/test_set\\00195.jpg", "label": "-1"}, {"dir": "./data/expand_data/test_set\\00196.jpg", "label": "-1"}, {"dir": "./data/expand_data/test_set\\00197.jpg", "label": "-1"}, {"dir": "./data/expand_data/test_set\\00198.jpg", "label": "-1"}, {"dir": "./data/expand_data/test_set\\00199.jpg", "label": "-1"}, {"dir": "./data/expand_data/test_set\\00200.jpg", "label": "-1"}, {"dir": "./data/expand_data/test_set\\00201.jpg", "label": "-1"}, {"dir": "./data/expand_data/test_set\\00202.jpg", "label": "-1"}, {"dir": "./data/expand_data/test_set\\00203.jpg", "label": "-1"}, {"dir": "./data/expand_data/test_set\\00204.jpg", "label": "-1"}, {"dir": "./data/expand_data/test_set\\00205.jpg", "label": "-1"}, {"dir": "./data/expand_data/test_set\\00206.jpg", "label": "-1"}, {"dir": "./data/expand_data/test_set\\00207.jpg", "label": "-1"}, {"dir": "./data/expand_data/test_set\\00208.jpg", "label": "-1"}, {"dir": "./data/expand_data/test_set\\00209.jpg", "label": "-1"}, {"dir": "./data/expand_data/test_set\\00210.jpg", "label": "-1"}, {"dir": "./data/expand_data/test_set\\00211.jpg", "label": "-1"}, {"dir": "./data/expand_data/test_set\\00212.jpg", "label": "-1"}, {"dir": "./data/expand_data/test_set\\00213.jpg", "label": "-1"}, {"dir": "./data/expand_data/test_set\\00214.jpg", "label": "-1"}, {"dir": "./data/expand_data/test_set\\00215.jpg", "label": "-1"}, {"dir": "./data/expand_data/test_set\\00216.jpg", "label": "-1"}, {"dir": "./data/expand_data/test_set\\00217.jpg", "label": "-1"}, {"dir": "./data/expand_data/test_set\\00218.jpg", "label": "-1"}, {"dir": "./data/expand_data/test_set\\00219.jpg", "label": "-1"}, {"dir": "./data/expand_data/test_set\\00220.jpg", "label": "-1"}, {"dir": "./data/expand_data/test_set\\00221.jpg", "label": "-1"}, {"dir": "./data/expand_data/test_set\\00222.jpg", "label": "-1"}, {"dir": "./data/expand_data/test_set\\00223.jpg", "label": "-1"}, {"dir": "./data/expand_data/test_set\\00224.jpg", "label": "-1"}, {"dir": "./data/expand_data/test_set\\00225.jpg", "label": "-1"}, {"dir": "./data/expand_data/test_set\\00226.jpg", "label": "-1"}, {"dir": "./data/expand_data/test_set\\00227.jpg", "label": "-1"}, {"dir": "./data/expand_data/test_set\\00228.jpg", "label": "-1"}, {"dir": "./data/expand_data/test_set\\00229.jpg", "label": "-1"}, {"dir": "./data/expand_data/test_set\\00230.jpg", "label": "-1"}, {"dir": "./data/expand_data/test_set\\00231.jpg", "label": "-1"}, {"dir": "./data/expand_data/test_set\\00232.jpg", "label": "-1"}, {"dir": "./data/expand_data/test_set\\00233.jpg", "label": "-1"}, {"dir": "./data/expand_data/test_set\\00234.jpg", "label": "-1"}, {"dir": "./data/expand_data/test_set\\00235.jpg", "label": "-1"}, {"dir": "./data/expand_data/test_set\\00236.jpg", "label": "-1"}, {"dir": "./data/expand_data/test_set\\00237.jpg", "label": "-1"}, {"dir": "./data/expand_data/test_set\\00238.jpg", "label": "-1"}, {"dir": "./data/expand_data/test_set\\00239.jpg", "label": "-1"}, {"dir": "./data/expand_data/test_set\\00240.jpg", "label": "-1"}, {"dir": "./data/expand_data/test_set\\00241.jpg", "label": "-1"}, {"dir": "./data/expand_data/test_set\\00242.jpg", "label": "-1"}, {"dir": "./data/expand_data/test_set\\00243.jpg", "label": "-1"}, {"dir": "./data/expand_data/test_set\\00244.jpg", "label": "-1"}, {"dir": "./data/expand_data/test_set\\00245.jpg", "label": "-1"}, {"dir": "./data/expand_data/test_set\\00246.jpg", "label": "-1"}, {"dir": "./data/expand_data/test_set\\00247.jpg", "label": "-1"}, {"dir": "./data/expand_data/test_set\\00248.jpg", "label": "-1"}, {"dir": "./data/expand_data/test_set\\00249.jpg", "label": "-1"}, {"dir": "./data/expand_data/test_set\\00250.jpg", "label": "-1"}, {"dir": "./data/expand_data/test_set\\00251.jpg", "label": "-1"}, {"dir": "./data/expand_data/test_set\\00252.jpg", "label": "-1"}, {"dir": "./data/expand_data/test_set\\00253.jpg", "label": "-1"}, {"dir": "./data/expand_data/test_set\\00254.jpg", "label": "-1"}, {"dir": "./data/expand_data/test_set\\00255.jpg", "label": "-1"}, {"dir": "./data/expand_data/test_set\\00256.jpg", "label": "-1"}, {"dir": "./data/expand_data/test_set\\00257.jpg", "label": "-1"}, {"dir": "./data/expand_data/test_set\\00258.jpg", "label": "-1"}, {"dir": "./data/expand_data/test_set\\00259.jpg", "label": "-1"}, {"dir": "./data/expand_data/test_set\\00260.jpg", "label": "-1"}, {"dir": "./data/expand_data/test_set\\00261.jpg", "label": "-1"}, {"dir": "./data/expand_data/test_set\\00262.jpg", "label": "-1"}, {"dir": "./data/expand_data/test_set\\00263.jpg", "label": "-1"}, {"dir": "./data/expand_data/test_set\\00264.jpg", "label": "-1"}, {"dir": "./data/expand_data/test_set\\00265.jpg", "label": "-1"}, {"dir": "./data/expand_data/test_set\\00266.jpg", "label": "-1"}, {"dir": "./data/expand_data/test_set\\00267.jpg", "label": "-1"}, {"dir": "./data/expand_data/test_set\\00268.jpg", "label": "-1"}, {"dir": "./data/expand_data/test_set\\00269.jpg", "label": "-1"}, {"dir": "./data/expand_data/test_set\\00270.jpg", "label": "-1"}, {"dir": "./data/expand_data/test_set\\00271.jpg", "label": "-1"}, {"dir": "./data/expand_data/test_set\\00272.jpg", "label": "-1"}, {"dir": "./data/expand_data/test_set\\00273.jpg", "label": "-1"}, {"dir": "./data/expand_data/test_set\\00274.jpg", "label": "-1"}, {"dir": "./data/expand_data/test_set\\00275.jpg", "label": "-1"}, {"dir": "./data/expand_data/test_set\\00276.jpg", "label": "-1"}, {"dir": "./data/expand_data/test_set\\00277.jpg", "label": "-1"}, {"dir": "./data/expand_data/test_set\\00278.jpg", "label": "-1"}, {"dir": "./data/expand_data/test_set\\00279.jpg", "label": "-1"}, {"dir": "./data/expand_data/test_set\\00280.jpg", "label": "-1"}, {"dir": "./data/expand_data/test_set\\00281.jpg", "label": "-1"}, {"dir": "./data/expand_data/test_set\\00282.jpg", "label": "-1"}, {"dir": "./data/expand_data/test_set\\00283.jpg", "label": "-1"}, {"dir": "./data/expand_data/test_set\\00284.jpg", "label": "-1"}, {"dir": "./data/expand_data/test_set\\00285.jpg", "label": "-1"}, {"dir": "./data/expand_data/test_set\\00286.jpg", "label": "-1"}, {"dir": "./data/expand_data/test_set\\00287.jpg", "label": "-1"}, {"dir": "./data/expand_data/test_set\\00288.jpg", "label": "-1"}, {"dir": "./data/expand_data/test_set\\00289.jpg", "label": "-1"}, {"dir": "./data/expand_data/test_set\\00290.jpg", "label": "-1"}, {"dir": "./data/expand_data/test_set\\00291.jpg", "label": "-1"}, {"dir": "./data/expand_data/test_set\\00292.jpg", "label": "-1"}, {"dir": "./data/expand_data/test_set\\00293.jpg", "label": "-1"}, {"dir": "./data/expand_data/test_set\\00294.jpg", "label": "-1"}, {"dir": "./data/expand_data/test_set\\00295.jpg", "label": "-1"}, {"dir": "./data/expand_data/test_set\\00296.jpg", "label": "-1"}, {"dir": "./data/expand_data/test_set\\00297.jpg", "label": "-1"}, {"dir": "./data/expand_data/test_set\\00298.jpg", "label": "-1"}, {"dir": "./data/expand_data/test_set\\00299.jpg", "label": "-1"}, {"dir": "./data/expand_data/test_set\\00300.jpg", "label": "-1"}, {"dir": "./data/expand_data/test_set\\00301.jpg", "label": "-1"}, {"dir": "./data/expand_data/test_set\\00302.jpg", "label": "-1"}, {"dir": "./data/expand_data/test_set\\00303.jpg", "label": "-1"}, {"dir": "./data/expand_data/test_set\\00304.jpg", "label": "-1"}, {"dir": "./data/expand_data/test_set\\00305.jpg", "label": "-1"}, {"dir": "./data/expand_data/test_set\\00306.jpg", "label": "-1"}, {"dir": "./data/expand_data/test_set\\00307.jpg", "label": "-1"}, {"dir": "./data/expand_data/test_set\\00308.jpg", "label": "-1"}, {"dir": "./data/expand_data/test_set\\00309.jpg", "label": "-1"}, {"dir": "./data/expand_data/test_set\\00310.jpg", "label": "-1"}, {"dir": "./data/expand_data/test_set\\00311.jpg", "label": "-1"}, {"dir": "./data/expand_data/test_set\\00312.jpg", "label": "-1"}, {"dir": "./data/expand_data/test_set\\00313.jpg", "label": "-1"}, {"dir": "./data/expand_data/test_set\\00314.jpg", "label": "-1"}, {"dir": "./data/expand_data/test_set\\00315.jpg", "label": "-1"}, {"dir": "./data/expand_data/test_set\\00316.jpg", "label": "-1"}, {"dir": "./data/expand_data/test_set\\00317.jpg", "label": "-1"}, {"dir": "./data/expand_data/test_set\\00318.jpg", "label": "-1"}, {"dir": "./data/expand_data/test_set\\00319.jpg", "label": "-1"}, {"dir": "./data/expand_data/test_set\\00320.jpg", "label": "-1"}, {"dir": "./data/expand_data/test_set\\00321.jpg", "label": "-1"}, {"dir": "./data/expand_data/test_set\\00322.jpg", "label": "-1"}, {"dir": "./data/expand_data/test_set\\00323.jpg", "label": "-1"}, {"dir": "./data/expand_data/test_set\\00324.jpg", "label": "-1"}, {"dir": "./data/expand_data/test_set\\00325.jpg", "label": "-1"}, {"dir": "./data/expand_data/test_set\\00326.jpg", "label": "-1"}, {"dir": "./data/expand_data/test_set\\00327.jpg", "label": "-1"}, {"dir": "./data/expand_data/test_set\\00328.jpg", "label": "-1"}, {"dir": "./data/expand_data/test_set\\00329.jpg", "label": "-1"}, {"dir": "./data/expand_data/test_set\\00330.jpg", "label": "-1"}, {"dir": "./data/expand_data/test_set\\00331.jpg", "label": "-1"}, {"dir": "./data/expand_data/test_set\\00332.jpg", "label": "-1"}, {"dir": "./data/expand_data/test_set\\00333.jpg", "label": "-1"}, {"dir": "./data/expand_data/test_set\\00334.jpg", "label": "-1"}, {"dir": "./data/expand_data/test_set\\00335.jpg", "label": "-1"}, {"dir": "./data/expand_data/test_set\\00336.jpg", "label": "-1"}, {"dir": "./data/expand_data/test_set\\00337.jpg", "label": "-1"}, {"dir": "./data/expand_data/test_set\\00338.jpg", "label": "-1"}, {"dir": "./data/expand_data/test_set\\00339.jpg", "label": "-1"}, {"dir": "./data/expand_data/test_set\\00340.jpg", "label": "-1"}, {"dir": "./data/expand_data/test_set\\00341.jpg", "label": "-1"}, {"dir": "./data/expand_data/test_set\\00342.jpg", "label": "-1"}, {"dir": "./data/expand_data/test_set\\00343.jpg", "label": "-1"}, {"dir": "./data/expand_data/test_set\\00344.jpg", "label": "-1"}, {"dir": "./data/expand_data/test_set\\00345.jpg", "label": "-1"}, {"dir": "./data/expand_data/test_set\\00346.jpg", "label": "-1"}, {"dir": "./data/expand_data/test_set\\00347.jpg", "label": "-1"}, {"dir": "./data/expand_data/test_set\\00348.jpg", "label": "-1"}, {"dir": "./data/expand_data/test_set\\00349.jpg", "label": "-1"}, {"dir": "./data/expand_data/test_set\\00350.jpg", "label": "-1"}, {"dir": "./data/expand_data/test_set\\00351.jpg", "label": "-1"}, {"dir": "./data/expand_data/test_set\\00352.jpg", "label": "-1"}, {"dir": "./data/expand_data/test_set\\00353.jpg", "label": "-1"}, {"dir": "./data/expand_data/test_set\\00354.jpg", "label": "-1"}, {"dir": "./data/expand_data/test_set\\00355.jpg", "label": "-1"}, {"dir": "./data/expand_data/test_set\\00356.jpg", "label": "-1"}, {"dir": "./data/expand_data/test_set\\00357.jpg", "label": "-1"}, {"dir": "./data/expand_data/test_set\\00358.jpg", "label": "-1"}, {"dir": "./data/expand_data/test_set\\00359.jpg", "label": "-1"}, {"dir": "./data/expand_data/test_set\\00360.jpg", "label": "-1"}, {"dir": "./data/expand_data/test_set\\00361.jpg", "label": "-1"}, {"dir": "./data/expand_data/test_set\\00362.jpg", "label": "-1"}, {"dir": "./data/expand_data/test_set\\00363.jpg", "label": "-1"}, {"dir": "./data/expand_data/test_set\\00364.jpg", "label": "-1"}, {"dir": "./data/expand_data/test_set\\00365.jpg", "label": "-1"}, {"dir": "./data/expand_data/test_set\\00366.jpg", "label": "-1"}, {"dir": "./data/expand_data/test_set\\00367.jpg", "label": "-1"}, {"dir": "./data/expand_data/test_set\\00368.jpg", "label": "-1"}, {"dir": "./data/expand_data/test_set\\00369.jpg", "label": "-1"}, {"dir": "./data/expand_data/test_set\\00370.jpg", "label": "-1"}, {"dir": "./data/expand_data/test_set\\00371.jpg", "label": "-1"}, {"dir": "./data/expand_data/test_set\\00372.jpg", "label": "-1"}, {"dir": "./data/expand_data/test_set\\00373.jpg", "label": "-1"}, {"dir": "./data/expand_data/test_set\\00374.jpg", "label": "-1"}, {"dir": "./data/expand_data/test_set\\00375.jpg", "label": "-1"}, {"dir": "./data/expand_data/test_set\\00376.jpg", "label": "-1"}, {"dir": "./data/expand_data/test_set\\00377.jpg", "label": "-1"}, {"dir": "./data/expand_data/test_set\\00378.jpg", "label": "-1"}, {"dir": "./data/expand_data/test_set\\00379.jpg", "label": "-1"}, {"dir": "./data/expand_data/test_set\\00380.jpg", "label": "-1"}, {"dir": "./data/expand_data/test_set\\00381.jpg", "label": "-1"}, {"dir": "./data/expand_data/test_set\\00382.jpg", "label": "-1"}, {"dir": "./data/expand_data/test_set\\00383.jpg", "label": "-1"}, {"dir": "./data/expand_data/test_set\\00384.jpg", "label": "-1"}, {"dir": "./data/expand_data/test_set\\00385.jpg", "label": "-1"}, {"dir": "./data/expand_data/test_set\\00386.jpg", "label": "-1"}, {"dir": "./data/expand_data/test_set\\00387.jpg", "label": "-1"}, {"dir": "./data/expand_data/test_set\\00388.jpg", "label": "-1"}, {"dir": "./data/expand_data/test_set\\00389.jpg", "label": "-1"}, {"dir": "./data/expand_data/test_set\\00390.jpg", "label": "-1"}, {"dir": "./data/expand_data/test_set\\00391.jpg", "label": "-1"}, {"dir": "./data/expand_data/test_set\\00392.jpg", "label": "-1"}, {"dir": "./data/expand_data/test_set\\00393.jpg", "label": "-1"}, {"dir": "./data/expand_data/test_set\\00394.jpg", "label": "-1"}, {"dir": "./data/expand_data/test_set\\00395.jpg", "label": "-1"}, {"dir": "./data/expand_data/test_set\\00396.jpg", "label": "-1"}, {"dir": "./data/expand_data/test_set\\00397.jpg", "label": "-1"}, {"dir": "./data/expand_data/test_set\\00398.jpg", "label": "-1"}, {"dir": "./data/expand_data/test_set\\00399.jpg", "label": "-1"}, {"dir": "./data/expand_data/test_set\\00400.jpg", "label": "-1"}, {"dir": "./data/expand_data/test_set\\00401.jpg", "label": "-1"}, {"dir": "./data/expand_data/test_set\\00402.jpg", "label": "-1"}, {"dir": "./data/expand_data/test_set\\00403.jpg", "label": "-1"}, {"dir": "./data/expand_data/test_set\\00404.jpg", "label": "-1"}, {"dir": "./data/expand_data/test_set\\00405.jpg", "label": "-1"}, {"dir": "./data/expand_data/test_set\\00406.jpg", "label": "-1"}, {"dir": "./data/expand_data/test_set\\00407.jpg", "label": "-1"}, {"dir": "./data/expand_data/test_set\\00408.jpg", "label": "-1"}, {"dir": "./data/expand_data/test_set\\00409.jpg", "label": "-1"}, {"dir": "./data/expand_data/test_set\\00410.jpg", "label": "-1"}, {"dir": "./data/expand_data/test_set\\00411.jpg", "label": "-1"}, {"dir": "./data/expand_data/test_set\\00412.jpg", "label": "-1"}, {"dir": "./data/expand_data/test_set\\00413.jpg", "label": "-1"}, {"dir": "./data/expand_data/test_set\\00414.jpg", "label": "-1"}, {"dir": "./data/expand_data/test_set\\00415.jpg", "label": "-1"}, {"dir": "./data/expand_data/test_set\\00416.jpg", "label": "-1"}, {"dir": "./data/expand_data/test_set\\00417.jpg", "label": "-1"}, {"dir": "./data/expand_data/test_set\\00418.jpg", "label": "-1"}, {"dir": "./data/expand_data/test_set\\00419.jpg", "label": "-1"}, {"dir": "./data/expand_data/test_set\\00420.jpg", "label": "-1"}, {"dir": "./data/expand_data/test_set\\00421.jpg", "label": "-1"}, {"dir": "./data/expand_data/test_set\\00422.jpg", "label": "-1"}, {"dir": "./data/expand_data/test_set\\00423.jpg", "label": "-1"}, {"dir": "./data/expand_data/test_set\\00424.jpg", "label": "-1"}, {"dir": "./data/expand_data/test_set\\00425.jpg", "label": "-1"}, {"dir": "./data/expand_data/test_set\\00426.jpg", "label": "-1"}, {"dir": "./data/expand_data/test_set\\00427.jpg", "label": "-1"}, {"dir": "./data/expand_data/test_set\\00428.jpg", "label": "-1"}, {"dir": "./data/expand_data/test_set\\00429.jpg", "label": "-1"}, {"dir": "./data/expand_data/test_set\\00430.jpg", "label": "-1"}, {"dir": "./data/expand_data/test_set\\00431.jpg", "label": "-1"}, {"dir": "./data/expand_data/test_set\\00432.jpg", "label": "-1"}, {"dir": "./data/expand_data/test_set\\00433.jpg", "label": "-1"}, {"dir": "./data/expand_data/test_set\\00434.jpg", "label": "-1"}, {"dir": "./data/expand_data/test_set\\00435.jpg", "label": "-1"}, {"dir": "./data/expand_data/test_set\\00436.jpg", "label": "-1"}, {"dir": "./data/expand_data/test_set\\00437.jpg", "label": "-1"}, {"dir": "./data/expand_data/test_set\\00438.jpg", "label": "-1"}, {"dir": "./data/expand_data/test_set\\00439.jpg", "label": "-1"}, {"dir": "./data/expand_data/test_set\\00440.jpg", "label": "-1"}, {"dir": "./data/expand_data/test_set\\00441.jpg", "label": "-1"}, {"dir": "./data/expand_data/test_set\\00442.jpg", "label": "-1"}, {"dir": "./data/expand_data/test_set\\00443.jpg", "label": "-1"}, {"dir": "./data/expand_data/test_set\\00444.jpg", "label": "-1"}, {"dir": "./data/expand_data/test_set\\00445.jpg", "label": "-1"}, {"dir": "./data/expand_data/test_set\\00446.jpg", "label": "-1"}, {"dir": "./data/expand_data/test_set\\00447.jpg", "label": "-1"}, {"dir": "./data/expand_data/test_set\\00448.jpg", "label": "-1"}, {"dir": "./data/expand_data/test_set\\00449.jpg", "label": "-1"}, {"dir": "./data/expand_data/test_set\\00450.jpg", "label": "-1"}, {"dir": "./data/expand_data/test_set\\00451.jpg", "label": "-1"}, {"dir": "./data/expand_data/test_set\\00452.jpg", "label": "-1"}, {"dir": "./data/expand_data/test_set\\00453.jpg", "label": "-1"}, {"dir": "./data/expand_data/test_set\\00454.jpg", "label": "-1"}, {"dir": "./data/expand_data/test_set\\00455.jpg", "label": "-1"}, {"dir": "./data/expand_data/test_set\\00456.jpg", "label": "-1"}, {"dir": "./data/expand_data/test_set\\00457.jpg", "label": "-1"}, {"dir": "./data/expand_data/test_set\\00458.jpg", "label": "-1"}, {"dir": "./data/expand_data/test_set\\00459.jpg", "label": "-1"}, {"dir": "./data/expand_data/test_set\\00460.jpg", "label": "-1"}, {"dir": "./data/expand_data/test_set\\00461.jpg", "label": "-1"}, {"dir": "./data/expand_data/test_set\\00462.jpg", "label": "-1"}, {"dir": "./data/expand_data/test_set\\00463.jpg", "label": "-1"}, {"dir": "./data/expand_data/test_set\\00464.jpg", "label": "-1"}, {"dir": "./data/expand_data/test_set\\00465.jpg", "label": "-1"}, {"dir": "./data/expand_data/test_set\\00466.jpg", "label": "-1"}, {"dir": "./data/expand_data/test_set\\00467.jpg", "label": "-1"}, {"dir": "./data/expand_data/test_set\\00468.jpg", "label": "-1"}, {"dir": "./data/expand_data/test_set\\00469.jpg", "label": "-1"}, {"dir": "./data/expand_data/test_set\\00470.jpg", "label": "-1"}, {"dir": "./data/expand_data/test_set\\00471.jpg", "label": "-1"}, {"dir": "./data/expand_data/test_set\\00472.jpg", "label": "-1"}, {"dir": "./data/expand_data/test_set\\00473.jpg", "label": "-1"}, {"dir": "./data/expand_data/test_set\\00474.jpg", "label": "-1"}, {"dir": "./data/expand_data/test_set\\00475.jpg", "label": "-1"}, {"dir": "./data/expand_data/test_set\\00476.jpg", "label": "-1"}, {"dir": "./data/expand_data/test_set\\00477.jpg", "label": "-1"}, {"dir": "./data/expand_data/test_set\\00478.jpg", "label": "-1"}, {"dir": "./data/expand_data/test_set\\00479.jpg", "label": "-1"}, {"dir": "./data/expand_data/test_set\\00480.jpg", "label": "-1"}, {"dir": "./data/expand_data/test_set\\00481.jpg", "label": "-1"}, {"dir": "./data/expand_data/test_set\\00482.jpg", "label": "-1"}, {"dir": "./data/expand_data/test_set\\00483.jpg", "label": "-1"}, {"dir": "./data/expand_data/test_set\\00484.jpg", "label": "-1"}, {"dir": "./data/expand_data/test_set\\00485.jpg", "label": "-1"}, {"dir": "./data/expand_data/test_set\\00486.jpg", "label": "-1"}, {"dir": "./data/expand_data/test_set\\00487.jpg", "label": "-1"}, {"dir": "./data/expand_data/test_set\\00488.jpg", "label": "-1"}, {"dir": "./data/expand_data/test_set\\00489.jpg", "label": "-1"}, {"dir": "./data/expand_data/test_set\\00490.jpg", "label": "-1"}, {"dir": "./data/expand_data/test_set\\00491.jpg", "label": "-1"}, {"dir": "./data/expand_data/test_set\\00492.jpg", "label": "-1"}, {"dir": "./data/expand_data/test_set\\00493.jpg", "label": "-1"}, {"dir": "./data/expand_data/test_set\\00494.jpg", "label": "-1"}, {"dir": "./data/expand_data/test_set\\00495.jpg", "label": "-1"}, {"dir": "./data/expand_data/test_set\\00496.jpg", "label": "-1"}, {"dir": "./data/expand_data/test_set\\00497.jpg", "label": "-1"}, {"dir": "./data/expand_data/test_set\\00498.jpg", "label": "-1"}, {"dir": "./data/expand_data/test_set\\00499.jpg", "label": "-1"}, {"dir": "./data/expand_data/test_set\\00500.jpg", "label": "-1"}, {"dir": "./data/expand_data/test_set\\00501.jpg", "label": "-1"}, {"dir": "./data/expand_data/test_set\\00502.jpg", "label": "-1"}, {"dir": "./data/expand_data/test_set\\00503.jpg", "label": "-1"}, {"dir": "./data/expand_data/test_set\\00504.jpg", "label": "-1"}, {"dir": "./data/expand_data/test_set\\00505.jpg", "label": "-1"}, {"dir": "./data/expand_data/test_set\\00506.jpg", "label": "-1"}, {"dir": "./data/expand_data/test_set\\00507.jpg", "label": "-1"}, {"dir": "./data/expand_data/test_set\\00508.jpg", "label": "-1"}, {"dir": "./data/expand_data/test_set\\00509.jpg", "label": "-1"}, {"dir": "./data/expand_data/test_set\\00510.jpg", "label": "-1"}, {"dir": "./data/expand_data/test_set\\00511.jpg", "label": "-1"}, {"dir": "./data/expand_data/test_set\\00512.jpg", "label": "-1"}, {"dir": "./data/expand_data/test_set\\00513.jpg", "label": "-1"}, {"dir": "./data/expand_data/test_set\\00514.jpg", "label": "-1"}, {"dir": "./data/expand_data/test_set\\00515.jpg", "label": "-1"}, {"dir": "./data/expand_data/test_set\\00516.jpg", "label": "-1"}, {"dir": "./data/expand_data/test_set\\00517.jpg", "label": "-1"}, {"dir": "./data/expand_data/test_set\\00518.jpg", "label": "-1"}, {"dir": "./data/expand_data/test_set\\00519.jpg", "label": "-1"}, {"dir": "./data/expand_data/test_set\\00520.jpg", "label": "-1"}, {"dir": "./data/expand_data/test_set\\00521.jpg", "label": "-1"}, {"dir": "./data/expand_data/test_set\\00522.jpg", "label": "-1"}, {"dir": "./data/expand_data/test_set\\00523.jpg", "label": "-1"}, {"dir": "./data/expand_data/test_set\\00524.jpg", "label": "-1"}, {"dir": "./data/expand_data/test_set\\00525.jpg", "label": "-1"}, {"dir": "./data/expand_data/test_set\\00526.jpg", "label": "-1"}, {"dir": "./data/expand_data/test_set\\00527.jpg", "label": "-1"}, {"dir": "./data/expand_data/test_set\\00528.jpg", "label": "-1"}, {"dir": "./data/expand_data/test_set\\00529.jpg", "label": "-1"}, {"dir": "./data/expand_data/test_set\\00530.jpg", "label": "-1"}, {"dir": "./data/expand_data/test_set\\00531.jpg", "label": "-1"}, {"dir": "./data/expand_data/test_set\\00532.jpg", "label": "-1"}, {"dir": "./data/expand_data/test_set\\00533.jpg", "label": "-1"}, {"dir": "./data/expand_data/test_set\\00534.jpg", "label": "-1"}, {"dir": "./data/expand_data/test_set\\00535.jpg", "label": "-1"}, {"dir": "./data/expand_data/test_set\\00536.jpg", "label": "-1"}, {"dir": "./data/expand_data/test_set\\00537.jpg", "label": "-1"}, {"dir": "./data/expand_data/test_set\\00538.jpg", "label": "-1"}, {"dir": "./data/expand_data/test_set\\00539.jpg", "label": "-1"}, {"dir": "./data/expand_data/test_set\\00540.jpg", "label": "-1"}, {"dir": "./data/expand_data/test_set\\00541.jpg", "label": "-1"}, {"dir": "./data/expand_data/test_set\\00542.jpg", "label": "-1"}, {"dir": "./data/expand_data/test_set\\00543.jpg", "label": "-1"}, {"dir": "./data/expand_data/test_set\\00544.jpg", "label": "-1"}, {"dir": "./data/expand_data/test_set\\00545.jpg", "label": "-1"}, {"dir": "./data/expand_data/test_set\\00546.jpg", "label": "-1"}, {"dir": "./data/expand_data/test_set\\00547.jpg", "label": "-1"}, {"dir": "./data/expand_data/test_set\\00548.jpg", "label": "-1"}, {"dir": "./data/expand_data/test_set\\00549.jpg", "label": "-1"}, {"dir": "./data/expand_data/test_set\\00550.jpg", "label": "-1"}, {"dir": "./data/expand_data/test_set\\00551.jpg", "label": "-1"}, {"dir": "./data/expand_data/test_set\\00552.jpg", "label": "-1"}, {"dir": "./data/expand_data/test_set\\00553.jpg", "label": "-1"}, {"dir": "./data/expand_data/test_set\\00554.jpg", "label": "-1"}, {"dir": "./data/expand_data/test_set\\00555.jpg", "label": "-1"}, {"dir": "./data/expand_data/test_set\\00556.jpg", "label": "-1"}, {"dir": "./data/expand_data/test_set\\00557.jpg", "label": "-1"}, {"dir": "./data/expand_data/test_set\\00558.jpg", "label": "-1"}, {"dir": "./data/expand_data/test_set\\00559.jpg", "label": "-1"}, {"dir": "./data/expand_data/test_set\\00560.jpg", "label": "-1"}, {"dir": "./data/expand_data/test_set\\00561.jpg", "label": "-1"}, {"dir": "./data/expand_data/test_set\\00562.jpg", "label": "-1"}, {"dir": "./data/expand_data/test_set\\00563.jpg", "label": "-1"}, {"dir": "./data/expand_data/test_set\\00564.jpg", "label": "-1"}, {"dir": "./data/expand_data/test_set\\00565.jpg", "label": "-1"}, {"dir": "./data/expand_data/test_set\\00566.jpg", "label": "-1"}, {"dir": "./data/expand_data/test_set\\00567.jpg", "label": "-1"}, {"dir": "./data/expand_data/test_set\\00568.jpg", "label": "-1"}, {"dir": "./data/expand_data/test_set\\00569.jpg", "label": "-1"}, {"dir": "./data/expand_data/test_set\\00570.jpg", "label": "-1"}, {"dir": "./data/expand_data/test_set\\00571.jpg", "label": "-1"}, {"dir": "./data/expand_data/test_set\\00572.jpg", "label": "-1"}, {"dir": "./data/expand_data/test_set\\00573.jpg", "label": "-1"}, {"dir": "./data/expand_data/test_set\\00574.jpg", "label": "-1"}, {"dir": "./data/expand_data/test_set\\00575.jpg", "label": "-1"}, {"dir": "./data/expand_data/test_set\\00576.jpg", "label": "-1"}, {"dir": "./data/expand_data/test_set\\00577.jpg", "label": "-1"}, {"dir": "./data/expand_data/test_set\\00578.jpg", "label": "-1"}, {"dir": "./data/expand_data/test_set\\00579.jpg", "label": "-1"}, {"dir": "./data/expand_data/test_set\\00580.jpg", "label": "-1"}, {"dir": "./data/expand_data/test_set\\00581.jpg", "label": "-1"}, {"dir": "./data/expand_data/test_set\\00582.jpg", "label": "-1"}, {"dir": "./data/expand_data/test_set\\00583.jpg", "label": "-1"}, {"dir": "./data/expand_data/test_set\\00584.jpg", "label": "-1"}, {"dir": "./data/expand_data/test_set\\00585.jpg", "label": "-1"}, {"dir": "./data/expand_data/test_set\\00586.jpg", "label": "-1"}, {"dir": "./data/expand_data/test_set\\00587.jpg", "label": "-1"}, {"dir": "./data/expand_data/test_set\\00588.jpg", "label": "-1"}, {"dir": "./data/expand_data/test_set\\00589.jpg", "label": "-1"}, {"dir": "./data/expand_data/test_set\\00590.jpg", "label": "-1"}, {"dir": "./data/expand_data/test_set\\00591.jpg", "label": "-1"}, {"dir": "./data/expand_data/test_set\\00592.jpg", "label": "-1"}, {"dir": "./data/expand_data/test_set\\00593.jpg", "label": "-1"}, {"dir": "./data/expand_data/test_set\\00594.jpg", "label": "-1"}, {"dir": "./data/expand_data/test_set\\00595.jpg", "label": "-1"}, {"dir": "./data/expand_data/test_set\\00596.jpg", "label": "-1"}, {"dir": "./data/expand_data/test_set\\00597.jpg", "label": "-1"}, {"dir": "./data/expand_data/test_set\\00598.jpg", "label": "-1"}, {"dir": "./data/expand_data/test_set\\00599.jpg", "label": "-1"}, {"dir": "./data/expand_data/test_set\\00600.jpg", "label": "-1"}, {"dir": "./data/expand_data/test_set\\00601.jpg", "label": "-1"}, {"dir": "./data/expand_data/test_set\\00602.jpg", "label": "-1"}, {"dir": "./data/expand_data/test_set\\00603.jpg", "label": "-1"}, {"dir": "./data/expand_data/test_set\\00604.jpg", "label": "-1"}, {"dir": "./data/expand_data/test_set\\00605.jpg", "label": "-1"}, {"dir": "./data/expand_data/test_set\\00606.jpg", "label": "-1"}, {"dir": "./data/expand_data/test_set\\00607.jpg", "label": "-1"}, {"dir": "./data/expand_data/test_set\\00608.jpg", "label": "-1"}, {"dir": "./data/expand_data/test_set\\00609.jpg", "label": "-1"}, {"dir": "./data/expand_data/test_set\\00610.jpg", "label": "-1"}, {"dir": "./data/expand_data/test_set\\00611.jpg", "label": "-1"}, {"dir": "./data/expand_data/test_set\\00612.jpg", "label": "-1"}, {"dir": "./data/expand_data/test_set\\00613.jpg", "label": "-1"}, {"dir": "./data/expand_data/test_set\\00614.jpg", "label": "-1"}, {"dir": "./data/expand_data/test_set\\00615.jpg", "label": "-1"}, {"dir": "./data/expand_data/test_set\\00616.jpg", "label": "-1"}, {"dir": "./data/expand_data/test_set\\00617.jpg", "label": "-1"}, {"dir": "./data/expand_data/test_set\\00618.jpg", "label": "-1"}, {"dir": "./data/expand_data/test_set\\00619.jpg", "label": "-1"}, {"dir": "./data/expand_data/test_set\\00620.jpg", "label": "-1"}, {"dir": "./data/expand_data/test_set\\00621.jpg", "label": "-1"}, {"dir": "./data/expand_data/test_set\\00622.jpg", "label": "-1"}, {"dir": "./data/expand_data/test_set\\00623.jpg", "label": "-1"}, {"dir": "./data/expand_data/test_set\\00624.jpg", "label": "-1"}, {"dir": "./data/expand_data/test_set\\00625.jpg", "label": "-1"}, {"dir": "./data/expand_data/test_set\\00626.jpg", "label": "-1"}, {"dir": "./data/expand_data/test_set\\00627.jpg", "label": "-1"}, {"dir": "./data/expand_data/test_set\\00628.jpg", "label": "-1"}, {"dir": "./data/expand_data/test_set\\00629.jpg", "label": "-1"}, {"dir": "./data/expand_data/test_set\\00630.jpg", "label": "-1"}, {"dir": "./data/expand_data/test_set\\00631.jpg", "label": "-1"}, {"dir": "./data/expand_data/test_set\\00632.jpg", "label": "-1"}, {"dir": "./data/expand_data/test_set\\00633.jpg", "label": "-1"}, {"dir": "./data/expand_data/test_set\\00634.jpg", "label": "-1"}, {"dir": "./data/expand_data/test_set\\00635.jpg", "label": "-1"}, {"dir": "./data/expand_data/test_set\\00636.jpg", "label": "-1"}, {"dir": "./data/expand_data/test_set\\00637.jpg", "label": "-1"}, {"dir": "./data/expand_data/test_set\\00638.jpg", "label": "-1"}, {"dir": "./data/expand_data/test_set\\00639.jpg", "label": "-1"}, {"dir": "./data/expand_data/test_set\\00640.jpg", "label": "-1"}, {"dir": "./data/expand_data/test_set\\00641.jpg", "label": "-1"}, {"dir": "./data/expand_data/test_set\\00642.jpg", "label": "-1"}, {"dir": "./data/expand_data/test_set\\00643.jpg", "label": "-1"}, {"dir": "./data/expand_data/test_set\\00644.jpg", "label": "-1"}, {"dir": "./data/expand_data/test_set\\00645.jpg", "label": "-1"}, {"dir": "./data/expand_data/test_set\\00646.jpg", "label": "-1"}, {"dir": "./data/expand_data/test_set\\00647.jpg", "label": "-1"}, {"dir": "./data/expand_data/test_set\\00648.jpg", "label": "-1"}, {"dir": "./data/expand_data/test_set\\00649.jpg", "label": "-1"}, {"dir": "./data/expand_data/test_set\\00650.jpg", "label": "-1"}, {"dir": "./data/expand_data/test_set\\00651.jpg", "label": "-1"}, {"dir": "./data/expand_data/test_set\\00652.jpg", "label": "-1"}, {"dir": "./data/expand_data/test_set\\00653.jpg", "label": "-1"}, {"dir": "./data/expand_data/test_set\\00654.jpg", "label": "-1"}, {"dir": "./data/expand_data/test_set\\00655.jpg", "label": "-1"}, {"dir": "./data/expand_data/test_set\\00656.jpg", "label": "-1"}, {"dir": "./data/expand_data/test_set\\00657.jpg", "label": "-1"}, {"dir": "./data/expand_data/test_set\\00658.jpg", "label": "-1"}, {"dir": "./data/expand_data/test_set\\00659.jpg", "label": "-1"}, {"dir": "./data/expand_data/test_set\\00660.jpg", "label": "-1"}, {"dir": "./data/expand_data/test_set\\00661.jpg", "label": "-1"}, {"dir": "./data/expand_data/test_set\\00662.jpg", "label": "-1"}, {"dir": "./data/expand_data/test_set\\00663.jpg", "label": "-1"}, {"dir": "./data/expand_data/test_set\\00664.jpg", "label": "-1"}, {"dir": "./data/expand_data/test_set\\00665.jpg", "label": "-1"}, {"dir": "./data/expand_data/test_set\\00666.jpg", "label": "-1"}, {"dir": "./data/expand_data/test_set\\00667.jpg", "label": "-1"}, {"dir": "./data/expand_data/test_set\\00668.jpg", "label": "-1"}, {"dir": "./data/expand_data/test_set\\00669.jpg", "label": "-1"}, {"dir": "./data/expand_data/test_set\\00670.jpg", "label": "-1"}, {"dir": "./data/expand_data/test_set\\00671.jpg", "label": "-1"}, {"dir": "./data/expand_data/test_set\\00672.jpg", "label": "-1"}, {"dir": "./data/expand_data/test_set\\00673.jpg", "label": "-1"}, {"dir": "./data/expand_data/test_set\\00674.jpg", "label": "-1"}, {"dir": "./data/expand_data/test_set\\00675.jpg", "label": "-1"}, {"dir": "./data/expand_data/test_set\\00676.jpg", "label": "-1"}, {"dir": "./data/expand_data/test_set\\00677.jpg", "label": "-1"}, {"dir": "./data/expand_data/test_set\\00678.jpg", "label": "-1"}, {"dir": "./data/expand_data/test_set\\00679.jpg", "label": "-1"}, {"dir": "./data/expand_data/test_set\\00680.jpg", "label": "-1"}, {"dir": "./data/expand_data/test_set\\00681.jpg", "label": "-1"}, {"dir": "./data/expand_data/test_set\\00682.jpg", "label": "-1"}, {"dir": "./data/expand_data/test_set\\00683.jpg", "label": "-1"}, {"dir": "./data/expand_data/test_set\\00684.jpg", "label": "-1"}, {"dir": "./data/expand_data/test_set\\00685.jpg", "label": "-1"}, {"dir": "./data/expand_data/test_set\\00686.jpg", "label": "-1"}, {"dir": "./data/expand_data/test_set\\00687.jpg", "label": "-1"}, {"dir": "./data/expand_data/test_set\\00688.jpg", "label": "-1"}, {"dir": "./data/expand_data/test_set\\00689.jpg", "label": "-1"}, {"dir": "./data/expand_data/test_set\\00690.jpg", "label": "-1"}, {"dir": "./data/expand_data/test_set\\00691.jpg", "label": "-1"}, {"dir": "./data/expand_data/test_set\\00692.jpg", "label": "-1"}, {"dir": "./data/expand_data/test_set\\00693.jpg", "label": "-1"}, {"dir": "./data/expand_data/test_set\\00694.jpg", "label": "-1"}, {"dir": "./data/expand_data/test_set\\00695.jpg", "label": "-1"}, {"dir": "./data/expand_data/test_set\\00696.jpg", "label": "-1"}, {"dir": "./data/expand_data/test_set\\00697.jpg", "label": "-1"}, {"dir": "./data/expand_data/test_set\\00698.jpg", "label": "-1"}, {"dir": "./data/expand_data/test_set\\00699.jpg", "label": "-1"}, {"dir": "./data/expand_data/test_set\\00700.jpg", "label": "-1"}, {"dir": "./data/expand_data/test_set\\00701.jpg", "label": "-1"}, {"dir": "./data/expand_data/test_set\\00702.jpg", "label": "-1"}, {"dir": "./data/expand_data/test_set\\00703.jpg", "label": "-1"}, {"dir": "./data/expand_data/test_set\\00704.jpg", "label": "-1"}, {"dir": "./data/expand_data/test_set\\00705.jpg", "label": "-1"}, {"dir": "./data/expand_data/test_set\\00706.jpg", "label": "-1"}, {"dir": "./data/expand_data/test_set\\00707.jpg", "label": "-1"}, {"dir": "./data/expand_data/test_set\\00708.jpg", "label": "-1"}, {"dir": "./data/expand_data/test_set\\00709.jpg", "label": "-1"}, {"dir": "./data/expand_data/test_set\\00710.jpg", "label": "-1"}, {"dir": "./data/expand_data/test_set\\00711.jpg", "label": "-1"}, {"dir": "./data/expand_data/test_set\\00712.jpg", "label": "-1"}, {"dir": "./data/expand_data/test_set\\00713.jpg", "label": "-1"}, {"dir": "./data/expand_data/test_set\\00714.jpg", "label": "-1"}, {"dir": "./data/expand_data/test_set\\00715.jpg", "label": "-1"}, {"dir": "./data/expand_data/test_set\\00716.jpg", "label": "-1"}, {"dir": "./data/expand_data/test_set\\00717.jpg", "label": "-1"}, {"dir": "./data/expand_data/test_set\\00718.jpg", "label": "-1"}, {"dir": "./data/expand_data/test_set\\00719.jpg", "label": "-1"}, {"dir": "./data/expand_data/test_set\\00720.jpg", "label": "-1"}, {"dir": "./data/expand_data/test_set\\00721.jpg", "label": "-1"}, {"dir": "./data/expand_data/test_set\\00722.jpg", "label": "-1"}, {"dir": "./data/expand_data/test_set\\00723.jpg", "label": "-1"}, {"dir": "./data/expand_data/test_set\\00724.jpg", "label": "-1"}, {"dir": "./data/expand_data/test_set\\00725.jpg", "label": "-1"}, {"dir": "./data/expand_data/test_set\\00726.jpg", "label": "-1"}, {"dir": "./data/expand_data/test_set\\00727.jpg", "label": "-1"}, {"dir": "./data/expand_data/test_set\\00728.jpg", "label": "-1"}, {"dir": "./data/expand_data/test_set\\00729.jpg", "label": "-1"}, {"dir": "./data/expand_data/test_set\\00730.jpg", "label": "-1"}, {"dir": "./data/expand_data/test_set\\00731.jpg", "label": "-1"}, {"dir": "./data/expand_data/test_set\\00732.jpg", "label": "-1"}, {"dir": "./data/expand_data/test_set\\00733.jpg", "label": "-1"}, {"dir": "./data/expand_data/test_set\\00734.jpg", "label": "-1"}, {"dir": "./data/expand_data/test_set\\00735.jpg", "label": "-1"}, {"dir": "./data/expand_data/test_set\\00736.jpg", "label": "-1"}, {"dir": "./data/expand_data/test_set\\00737.jpg", "label": "-1"}, {"dir": "./data/expand_data/test_set\\00738.jpg", "label": "-1"}, {"dir": "./data/expand_data/test_set\\00739.jpg", "label": "-1"}, {"dir": "./data/expand_data/test_set\\00740.jpg", "label": "-1"}, {"dir": "./data/expand_data/test_set\\00741.jpg", "label": "-1"}, {"dir": "./data/expand_data/test_set\\00742.jpg", "label": "-1"}, {"dir": "./data/expand_data/test_set\\00743.jpg", "label": "-1"}, {"dir": "./data/expand_data/test_set\\00744.jpg", "label": "-1"}, {"dir": "./data/expand_data/test_set\\00745.jpg", "label": "-1"}, {"dir": "./data/expand_data/test_set\\00746.jpg", "label": "-1"}, {"dir": "./data/expand_data/test_set\\00747.jpg", "label": "-1"}, {"dir": "./data/expand_data/test_set\\00748.jpg", "label": "-1"}, {"dir": "./data/expand_data/test_set\\00749.jpg", "label": "-1"}, {"dir": "./data/expand_data/test_set\\00750.jpg", "label": "-1"}, {"dir": "./data/expand_data/test_set\\00751.jpg", "label": "-1"}, {"dir": "./data/expand_data/test_set\\00752.jpg", "label": "-1"}, {"dir": "./data/expand_data/test_set\\00753.jpg", "label": "-1"}, {"dir": "./data/expand_data/test_set\\00754.jpg", "label": "-1"}, {"dir": "./data/expand_data/test_set\\00755.jpg", "label": "-1"}, {"dir": "./data/expand_data/test_set\\00756.jpg", "label": "-1"}, {"dir": "./data/expand_data/test_set\\00757.jpg", "label": "-1"}, {"dir": "./data/expand_data/test_set\\00758.jpg", "label": "-1"}, {"dir": "./data/expand_data/test_set\\00759.jpg", "label": "-1"}, {"dir": "./data/expand_data/test_set\\00760.jpg", "label": "-1"}, {"dir": "./data/expand_data/test_set\\00761.jpg", "label": "-1"}, {"dir": "./data/expand_data/test_set\\00762.jpg", "label": "-1"}, {"dir": "./data/expand_data/test_set\\00763.jpg", "label": "-1"}, {"dir": "./data/expand_data/test_set\\00764.jpg", "label": "-1"}, {"dir": "./data/expand_data/test_set\\00765.jpg", "label": "-1"}, {"dir": "./data/expand_data/test_set\\00766.jpg", "label": "-1"}, {"dir": "./data/expand_data/test_set\\00767.jpg", "label": "-1"}, {"dir": "./data/expand_data/test_set\\00768.jpg", "label": "-1"}, {"dir": "./data/expand_data/test_set\\00769.jpg", "label": "-1"}, {"dir": "./data/expand_data/test_set\\00770.jpg", "label": "-1"}, {"dir": "./data/expand_data/test_set\\00771.jpg", "label": "-1"}, {"dir": "./data/expand_data/test_set\\00772.jpg", "label": "-1"}, {"dir": "./data/expand_data/test_set\\00773.jpg", "label": "-1"}, {"dir": "./data/expand_data/test_set\\00774.jpg", "label": "-1"}, {"dir": "./data/expand_data/test_set\\00775.jpg", "label": "-1"}, {"dir": "./data/expand_data/test_set\\00776.jpg", "label": "-1"}, {"dir": "./data/expand_data/test_set\\00777.jpg", "label": "-1"}, {"dir": "./data/expand_data/test_set\\00778.jpg", "label": "-1"}, {"dir": "./data/expand_data/test_set\\00779.jpg", "label": "-1"}, {"dir": "./data/expand_data/test_set\\00780.jpg", "label": "-1"}, {"dir": "./data/expand_data/test_set\\00781.jpg", "label": "-1"}, {"dir": "./data/expand_data/test_set\\00782.jpg", "label": "-1"}, {"dir": "./data/expand_data/test_set\\00783.jpg", "label": "-1"}, {"dir": "./data/expand_data/test_set\\00784.jpg", "label": "-1"}, {"dir": "./data/expand_data/test_set\\00785.jpg", "label": "-1"}, {"dir": "./data/expand_data/test_set\\00786.jpg", "label": "-1"}, {"dir": "./data/expand_data/test_set\\00787.jpg", "label": "-1"}, {"dir": "./data/expand_data/test_set\\00788.jpg", "label": "-1"}, {"dir": "./data/expand_data/test_set\\00789.jpg", "label": "-1"}, {"dir": "./data/expand_data/test_set\\00790.jpg", "label": "-1"}, {"dir": "./data/expand_data/test_set\\00791.jpg", "label": "-1"}, {"dir": "./data/expand_data/test_set\\00792.jpg", "label": "-1"}, {"dir": "./data/expand_data/test_set\\00793.jpg", "label": "-1"}, {"dir": "./data/expand_data/test_set\\00794.jpg", "label": "-1"}, {"dir": "./data/expand_data/test_set\\00795.jpg", "label": "-1"}, {"dir": "./data/expand_data/test_set\\00796.jpg", "label": "-1"}, {"dir": "./data/expand_data/test_set\\00797.jpg", "label": "-1"}, {"dir": "./data/expand_data/test_set\\00798.jpg", "label": "-1"}, {"dir": "./data/expand_data/test_set\\00799.jpg", "label": "-1"}]